turbomoleio/__init__.py
turbomoleio/_version.py
turbomoleio/core/__init__.py
turbomoleio/core/base.py
turbomoleio/core/control.py
turbomoleio/core/datagroups.py
turbomoleio/core/molecule.py
turbomoleio/core/periodic.py
turbomoleio/core/symmetry.py
turbomoleio/core/utils.py
turbomoleio/core/data/__init__.py
turbomoleio/core/data/available_solvents.txt
turbomoleio/input/__init__.py
turbomoleio/input/define.py
turbomoleio/input/utils.py
turbomoleio/input/templates/__init__.py
turbomoleio/input/templates/dscf.yaml
turbomoleio/input/templates/dscf_escf.yaml
turbomoleio/input/templates/ridft.yaml
turbomoleio/input/templates/ridft_escf.yaml
turbomoleio/input/templates/ridft_rimp2.yaml
turbomoleio/output/__init__.py
turbomoleio/output/data.py
turbomoleio/output/files.py
turbomoleio/output/parser.py
turbomoleio/output/states.py
turbomoleio/testing/__init__.py
turbomoleio-1.6.0.dist-info/COPYING
turbomoleio-1.6.0.dist-info/METADATA
turbomoleio-1.6.0.dist-info/WHEEL
turbomoleio-1.6.0.dist-info/top_level.txt
turbomoleio-1.6.0.dist-info/RECORD
